Workbook

Sheet REGRAS_CST
A1: CST_IBS_CBS | B1: Descrição CST | C1: Redução de BC? | D1: Redução de Alíquota? | E1: Exclusão de BC? | F1: Tratamento (resumo) | G1: Fonte
A2: 000 | B2: Tributação integral | C2: NÃO | D2: NÃO | E2: NÃO | F2: Tributação integral | G2: https://dfe-portal.svrs.rs.gov.br/CFF/ClassificacaoTributaria
A3: 010 | B3: Tributação com alíquotas uniformes | C3: NÃO | D3: NÃO | E3: NÃO | F3: Tributação (alíquota uniforme) | G3: https://dfe-portal.svrs.rs.gov.br/CFF/ClassificacaoTributaria
A4: 011 | B4: Tributação com alíquotas uniformes reduzidas | C4: NÃO | D4: SIM | E4: NÃO | F4: Tributação com alíquota reduzida | G4: https://dfe-portal.svrs.rs.gov.br/CFF/ClassificacaoTributaria
A5: 200 | B5: Alíquota reduzida | C5: NÃO | D5: SIM | E5: NÃO | F5: Tributação com alíquota reduzida | G5: https://dfe-portal.svrs.rs.gov.br/CFF/ClassificacaoTributaria
A6: 220 | B6: Alíquota fixa | C6: NÃO | D6: NÃO | E6: NÃO | F6: Tributação com alíquota fixa | G6: https://dfe-portal.svrs.rs.gov.br/CFF/ClassificacaoTributaria
A7: 221 | B7: Alíquota fixa proporcional | C7: NÃO | D7: NÃO | E7: NÃO | F7: Tributação com alíquota fixa | G7: https://dfe-portal.svrs.rs.gov.br/CFF/ClassificacaoTributaria
A8: 222 | B8: Redução de Base de Cálculo | C8: SIM | D8: NÃO | E8: NÃO | F8: Tributação com redução de base (informar % redução) | G8: https://dfe-portal.svrs.rs.gov.br/CFF/ClassificacaoTributaria
A9: 400 | B9: Isenção | C9: NÃO | D9: NÃO | E9: NÃO | F9: Sem débito (isenção/imunidade/suspensão) | G9: https://dfe-portal.svrs.rs.gov.br/CFF/ClassificacaoTributaria
A10: 410 | B10: Imunidade e não incidência | C10: NÃO | D10: NÃO | E10: NÃO | F10: Sem débito (isenção/imunidade/suspensão) | G10: https://dfe-portal.svrs.rs.gov.br/CFF/ClassificacaoTributaria
A11: 510 | B11: Diferimento | C11: NÃO | D11: NÃO | E11: NÃO | F11: Diferimento | G11: https://dfe-portal.svrs.rs.gov.br/CFF/ClassificacaoTributaria
A12: 515 | B12: Diferimento com redução de alíquota | C12: NÃO | D12: SIM | E12: NÃO | F12: Diferimento + alíquota reduzida | G12: https://dfe-portal.svrs.rs.gov.br/CFF/ClassificacaoTributaria
... A19: 830 | B19: Exclusão da Base de Cálculo | C19: NÃO | D19: NÃO | E19: SIM | F19: Exclusão de base (base = 0 para a parcela excluída) | G19: https://dfe-portal.svrs.rs.gov.br/CFF/ClassificacaoTributaria

Sheet CLASSTRIB
A1: cClassTrib | B1: Descrição | C1: CST (derivado) | D1: Descrição CST | E1: Redução de BC? | F1: Redução de Alíquota? | G1: Exclusão de BC? | H1: Fonte
A2: 000001 | B2: Situações tributadas integralmente pelo IBS e CBS | C2: =LEFT(A2,3) -> 000 | D2: =IFERROR(VLOOKUP(C2,REGRAS_CST!$A$2:$B$200,2,FALSE),"") -> Tributação integral | E2: =IFERROR(VLOOKUP(C2,REGRAS_CST!$A$2:$C$200,3,FALSE),"") -> NÃO | F2: =IFERROR(VLOOKUP(C2,REGRAS_CST!$A$2:$D$200,4,FALSE),"") -> NÃO | G2: =IFERROR(VLOOKUP(C2,REGRAS_CST!$A$2:$E$200,5,FALSE),"") -> NÃO | H2: https://dfe-portal.svrs.rs.gov.br/CFF/ClassificacaoTributaria
A3: 000002 | B3: Exploração de via | C3: =LEFT(A3,3) -> 000 | D3: =IFERROR(VLOOKUP(C3,REGRAS_CST!$A$2:$B$200,2,FALSE),"") -> Tributação integral | E3: =IFERROR(VLOOKUP(C3,REGRAS_CST!$A$2:$C$200,3,FALSE),"") -> NÃO | F3: =IFERROR(VLOOKUP(C3,REGRAS_CST!$A$2:$D$200,4,FALSE),"") -> NÃO | G3: =IFERROR(VLOOKUP(C3,REGRAS_CST!$A$2:$E$200,5,FALSE),"") -> NÃO | H3: https://dfe-portal.svrs.rs.gov.br/CFF/ClassificacaoTributaria
A4: 000003 | B4: Regime automotivo - projetos incentivados (art. 311) | C4: =LEFT(A4,3) -> 000 | D4: =IFERROR(VLOOKUP(C4,REGRAS_CST!$A$2:$B$200,2,FALSE),"") -> Tributação integral | E4: =IFERROR(VLOOKUP(C4,REGRAS_CST!$A$2:$C$200,3,FALSE),"") -> NÃO | F4: =IFERROR(VLOOKUP(C4,REGRAS_CST!$A$2:$D$200,4,FALSE),"") -> NÃO | G4: =IFERROR(VLOOKUP(C4,REGRAS_CST!$A$2:$E$200,5,FALSE),"") -> NÃO | H4: https://dfe-portal.svrs.rs.gov.br/CFF/ClassificacaoTributaria
A5: 000004 | B5: Regime automotivo - projetos incentivados (art. 312) | C5: =LEFT(A5,3) -> 000 | D5: =IFERROR(VLOOKUP(C5,REGRAS_CST!$A$2:$B$200,2,FALSE),"") -> Tributação integral | E5: =IFERROR(VLOOKUP(C5,REGRAS_CST!$A$2:$C$200,3,FALSE),"") -> NÃO | F5: =IFERROR(VLOOKUP(C5,REGRAS_CST!$A$2:$D$200,4,FALSE),"") -> NÃO | G5: =IFERROR(VLOOKUP(C5,REGRAS_CST!$A$2:$E$200,5,FALSE),"") -> NÃO | H5: https://dfe-portal.svrs.rs.gov.br/CFF/ClassificacaoTributaria
A6: 010001 | B6: Operações do FGTS não realizadas pela Caixa Econômica Federal | C6: =LEFT(A6,3) -> 010 | D6: =IFERROR(VLOOKUP(C6,REGRAS_CST!$A$2:$B$200,2,FALSE),"") -> Tributação com alíquotas uniformes | E6: =IFERROR(VLOOKUP(C6,REGRAS_CST!$A$2:$C$200,3,FALSE),"") -> NÃO | F6: =IFERROR(VLOOKUP(C6,REGRAS_CST!$A$2:$D$200,4,FALSE),"") -> NÃO | G6: =IFERROR(VLOOKUP(C6,REGRAS_CST!$A$2:$E$200,5,FALSE),"") -> NÃO | H6: https://dfe-portal.svrs.rs.gov.br/CFF/ClassificacaoTributaria
A7: 010002 | B7: Operações do serviço financeiro | C7: =LEFT(A7,3) -> 010 | D7: =IFERROR(VLOOKUP(C7,REGRAS_CST!$A$2:$B$200,2,FALSE),"") -> Tributação com alíquotas uniformes | E7: =IFERROR(VLOOKUP(C7,REGRAS_CST!$A$2:$C$200,3,FALSE),"") -> NÃO | F7: =IFERROR(VLOOKUP(C7,REGRAS_CST!$A$2:$D$200,4,FALSE),"") -> NÃO | G7: =IFERROR(VLOOKUP(C7,REGRAS_CST!$A$2:$E$200,5,FALSE),"") -> NÃO | H7: https://dfe-portal.svrs.rs.gov.br/CFF/ClassificacaoTributaria
A8: 011001 | B8: Planos de assistência funerária | C8: =LEFT(A8,3) -> 011 | D8: =IFERROR(VLOOKUP(C8,REGRAS_CST!$A$2:$B$200,2,FALSE),"") -> Tributação com alíquotas uniformes reduzidas | E8: =IFERROR(VLOOKUP(C8,REGRAS_CST!$A$2:$C$200,3,FALSE),"") -> NÃO | F8: =IFERROR(VLOOKUP(C8,REGRAS_CST!$A$2:$D$200,4,FALSE),"") -> SIM | G8: =IFERROR(VLOOKUP(C8,REGRAS_CST!$A$2:$E$200,5,FALSE),"") -> NÃO | H8: https://dfe-portal.svrs.rs.gov.br/CFF/ClassificacaoTributaria
A9: 011002 | B9: Planos de assistência à saúde | C9: =LEFT(A9,3) -> 011 | D9: =IFERROR(VLOOKUP(C9,REGRAS_CST!$A$2:$B$200,2,FALSE),"") -> Tributação com alíquotas uniformes reduzidas | E9: =IFERROR(VLOOKUP(C9,REGRAS_CST!$A$2:$C$200,3,FALSE),"") -> NÃO | F9: =IFERROR(VLOOKUP(C9,REGRAS_CST!$A$2:$D$200,4,FALSE),"") -> SIM | G9: =IFERROR(VLOOKUP(C9,REGRAS_CST!$A$2:$E$200,5,FALSE),"") -> NÃO | H9: https://dfe-portal.svrs.rs.gov.br/CFF/ClassificacaoTributaria
A10: 011003 | B10: Intermediação de planos de assistência à saúde | C10: =LEFT(A10,3) -> 011 | D10: =IFERROR(VLOOKUP(C10,REGRAS_CST!$A$2:$B$200,2,FALSE),"") -> Tributação com alíquotas uniformes reduzidas | E10: =IFERROR(VLOOKUP(C10,REGRAS_CST!$A$2:$C$200,3,FALSE),"") -> NÃO | F10: =IFERROR(VLOOKUP(C10,REGRAS_CST!$A$2:$D$200,4,FALSE),"") -> SIM | G10: =IFERROR(VLOOKUP(C10,REGRAS_CST!$A$2:$E$200,5,FALSE),"") -> NÃO | H10: https://dfe-portal.svrs.rs.gov.br/CFF/ClassificacaoTributaria
A11: 011004 | B11: Concursos e prognósticos | C11: =LEFT(A11,3) -> 011 | D11: =IFERROR(VLOOKUP(C11,REGRAS_CST!$A$2:$B$200,2,FALSE),"") -> Tributação com alíquotas uniformes reduzidas | E11: =IFERROR(VLOOKUP(C11,REGRAS_CST!$A$2:$C$200,3,FALSE),"") -> NÃO | F11: =IFERROR(VLOOKUP(C11,REGRAS_CST!$A$2:$D$200,4,FALSE),"") -> SIM | G11: =IFERROR(VLOOKUP(C11,REGRAS_CST!$A$2:$E$200,5,FALSE),"") -> NÃO | H11: https://dfe-portal.svrs.rs.gov.br/CFF/ClassificacaoTributaria
A12: 011005 | B12: Planos de assistência à saúde de animais domésticos | C12: =LEFT(A12,3) -> 011 | D12: =IFERROR(VLOOKUP(C12,REGRAS_CST!$A$2:$B$200,2,FALSE),"") -> Tributação com alíquotas uniformes reduzidas | E12: =IFERROR(VLOOKUP(C12,REGRAS_CST!$A$2:$C$200,3,FALSE),"") -> NÃO | F12: =IFERROR(VLOOKUP(C12,REGRAS_CST!$A$2:$D$200,4,FALSE),"") -> SIM | G12: =IFERROR(VLOOKUP(C12,REGRAS_CST!$A$2:$E$200,5,FALSE),"") -> NÃO | H12: https://dfe-portal.svrs.rs.gov.br/CFF/ClassificacaoTributaria
A13: 200001 | B13: Aquisições realizadas entre empresas autorizadas a operar em zonas de processamento de exportação | C13: =LEFT(A13,3) -> 200 | D13: =IFERROR(VLOOKUP(C13,REGRAS_CST!$A$2:$B$200,2,FALSE),"") -> Alíquota reduzida | E13: =IFERROR(VLOOKUP(C13,REGRAS_CST!$A$2:$C$200,3,FALSE),"") -> NÃO | F13: =IFERROR(VLOOKUP(C13,REGRAS_CST!$A$2:$D$200,4,FALSE),"") -> SIM | G13: =IFERROR(VLOOKUP(C13,REGRAS_CST!$A$2:$E$200,5,FALSE),"") -> NÃO | H13: https://dfe-portal.svrs.rs.gov.br/CFF/ClassificacaoTributaria
... A146: 830001 | B146: Documento com exclusão da BC da CBS e do IBS de energia elétrica fornecida pela distribuidora à UC | C146: =LEFT(A146,3) -> 830 | D146: =IFERROR(VLOOKUP(C146,REGRAS_CST!$A$2:$B$200,2,FALSE),"") -> Exclusão da Base de Cálculo | E146: =IFERROR(VLOOKUP(C146,REGRAS_CST!$A$2:$C$200,3,FALSE),"") -> NÃO | F146: =IFERROR(VLOOKUP(C146,REGRAS_CST!$A$2:$D$200,4,FALSE),"") -> NÃO | G146: =IFERROR(VLOOKUP(C146,REGRAS_CST!$A$2:$E$200,5,FALSE),"") -> SIM | H146: https://dfe-portal.svrs.rs.gov.br/CFF/ClassificacaoTributaria

Sheet LANCAMENTOS
A1: Data | B1: Numero | C1: Item/Serviço | D1: cClassTrib | E1: CST (auto) | F1: Descrição CST | G1: Valor da operação | H1: Alíquota CBS (0,90%) | I1: Alíquota IBS (0,10%) | J1: % Redução BC (manual) | K1: Redução de BC permitida? | L1: Base CBS & IBS | M1: Valor CBS | N1: Valor IBS | O1: Validação BC | P1: Validação da Aliquota | Q1: Redução de Alíquota permitida? | R1: % Redução Alíquota (quando não estiver no dados da classtrib) | S1: Alíquota Efetiva CBS | T1: Alíquota Efetiva IBS | U1: % Redução Alíquota (auto) | V1: % Redução BC (auto)
E2: =IF(D2="","",LEFT(D2,3)) | F2: =IF(E2="","",IFERROR(VLOOKUP(E2,REGRAS_CST!$A$2:$B$200,2,FALSE),"")) | H2: 0.009 | I2: 0.001 | J2: 0 | K2: =IF(E2="","",IFERROR(VLOOKUP(E2,REGRAS_CST!$A$2:$C$200,3,FALSE),"")) | L2: =IF($G2="", "", $G2*(1-$V2)) | M2: =IF(OR($L2="",$S2=""),"",$L2*$S2) | N2: =IF(OR($L2="",$T2=""),"",$L2*$T2) | O2: =IF(D2="","", IF(AND(K2<>"SIM",V2>0),"ERRO: % BC > 0, mas NÃO permitida ❌", IF(AND(K2="SIM",V2=0),"ATENÇÃO: BC permitida, mas % = 0 🔎", "Base de cálculo aplicada corretamente ✅"))) | P2: =IF(D2="","", IF(AND(Q2<>"SIM",U2>0),"ERRO: % alíquota > 0, mas NÃO permitida ❌", IF(AND(Q2="SIM",U2=0),"ATENÇÃO: alíquota permitida, mas % = 0 🔎", "Alíquota aplicada corretamente ✅"))) | Q2: =IF(E2="","",IFERROR(VLOOKUP(E2,REGRAS_CST!$A$2:$D$200,4,FALSE),"")) | S2: =IF($H2="","",$H2*(1-$U2)) -> 0.009 | T2: =IF($I2="","",$I2*(1-$U2)) -> 0.001 | U2: =IFERROR(INDEX(BASE_CCLASSTRIB!$E:$E, MATCH(TEXT($D2,"000000"), BASE_CCLASSTRIB!$A:$A, 0))/100, 0) -> 0 | V2: =IFERROR(INDEX(BASE_CCLASSTRIB!$F:$F, MATCH(TEXT($D2,"000000"), BASE_CCLASSTRIB!$A:$A, 0))/100, 0) -> 0
E3: =IF(D3="","",LEFT(D3,3)) | F3: =IF(E3="","",IFERROR(VLOOKUP(E3,REGRAS_CST!$A$2:$B$200,2,FALSE),"")) | H3: 0.009 | I3: 0.001 | K3: =IF(E3="","",IFERROR(VLOOKUP(E3,REGRAS_CST!$A$2:$C$200,3,FALSE),"")) | L3: =IF($G3="", "", $G3*(1-$V3)) | M3: =IF(OR($L3="",$S3=""),"",$L3*$S3) | N3: =IF(OR($L3="",$T3=""),"",$L3*$T3) | O3: =IF(D3="","", IF(AND(K3<>"SIM",V3>0),"ERRO: % BC > 0, mas NÃO permitida ❌", IF(AND(K3="SIM",V3=0),"ATENÇÃO: BC permitida, mas % = 0 🔎", "Base de cálculo aplicada corretamente ✅"))) | P3: =IF(D3="","", IF(AND(Q3<>"SIM",U3>0),"ERRO: % alíquota > 0, mas NÃO permitida ❌", IF(AND(Q3="SIM",U3=0),"ATENÇÃO: alíquota permitida, mas % = 0 🔎", "Alíquota aplicada corretamente ✅"))) | Q3: =IF(E3="","",IFERROR(VLOOKUP(E3,REGRAS_CST!$A$2:$D$200,4,FALSE),"")) | S3: =IF($H3="","",$H3*(1-$U3)) -> 0.009 | T3: =IF($I3="","",$I3*(1-$U3)) -> 0.001 | U3: =IFERROR(INDEX(BASE_CCLASSTRIB!$E:$E, MATCH(TEXT($D3,"000000"), BASE_CCLASSTRIB!$A:$A, 0))/100, 0) -> 0 | V3: =IFERROR(INDEX(BASE_CCLASSTRIB!$F:$F, MATCH(TEXT($D3,"000000"), BASE_CCLASSTRIB!$A:$A, 0))/100, 0) -> 0
E4: =IF(D4="","",LEFT(D4,3)) | F4: =IF(E4="","",IFERROR(VLOOKUP(E4,REGRAS_CST!$A$2:$B$200,2,FALSE),"")) | H4: 0.009 | I4: 0.001 | K4: =IF(E4="","",IFERROR(VLOOKUP(E4,REGRAS_CST!$A$2:$C$200,3,FALSE),"")) | L4: =IF($G4="", "", $G4*(1-$V4)) | M4: =IF(OR($L4="",$S4=""),"",$L4*$S4) | N4: =IF(OR($L4="",$T4=""),"",$L4*$T4) | O4: =IF(D4="","", IF(AND(K4<>"SIM",V4>0),"ERRO: % BC > 0, mas NÃO permitida ❌", IF(AND(K4="SIM",V4=0),"ATENÇÃO: BC permitida, mas % = 0 🔎", "Base de cálculo aplicada corretamente ✅"))) | P4: =IF(D4="","", IF(AND(Q4<>"SIM",U4>0),"ERRO: % alíquota > 0, mas NÃO permitida ❌", IF(AND(Q4="SIM",U4=0),"ATENÇÃO: alíquota permitida, mas % = 0 🔎", "Alíquota aplicada corretamente ✅"))) | Q4: =IF(E4="","",IFERROR(VLOOKUP(E4,REGRAS_CST!$A$2:$D$200,4,FALSE),"")) | S4: =IF($H4="","",$H4*(1-$U4)) -> 0.009 | T4: =IF($I4="","",$I4*(1-$U4)) -> 0.001 | U4: =IFERROR(INDEX(BASE_CCLASSTRIB!$E:$E, MATCH(TEXT($D4,"000000"), BASE_CCLASSTRIB!$A:$A, 0))/100, 0) -> 0 | V4: =IFERROR(INDEX(BASE_CCLASSTRIB!$F:$F, MATCH(TEXT($D4,"000000"), BASE_CCLASSTRIB!$A:$A, 0))/100, 0) -> 0
E5: =IF(D5="","",LEFT(D5,3)) | F5: =IF(E5="","",IFERROR(VLOOKUP(E5,REGRAS_CST!$A$2:$B$200,2,FALSE),"")) | H5: 0.009 | I5: 0.001 | K5: =IF(E5="","",IFERROR(VLOOKUP(E5,REGRAS_CST!$A$2:$C$200,3,FALSE),"")) | L5: =IF($G5="", "", $G5*(1-$V5)) | M5: =IF(OR($L5="",$S5=""),"",$L5*$S5) | N5: =IF(OR($L5="",$T5=""),"",$L5*$T5) | O5: =IF(D5="","", IF(AND(K5<>"SIM",V5>0),"ERRO: % BC > 0, mas NÃO permitida ❌", IF(AND(K5="SIM",V5=0),"ATENÇÃO: BC permitida, mas % = 0 🔎", "Base de cálculo aplicada corretamente ✅"))) | P5: =IF(D5="","", IF(AND(Q5<>"SIM",U5>0),"ERRO: % alíquota > 0, mas NÃO permitida ❌", IF(AND(Q5="SIM",U5=0),"ATENÇÃO: alíquota permitida, mas % = 0 🔎", "Alíquota aplicada corretamente ✅"))) | Q5: =IF(E5="","",IFERROR(VLOOKUP(E5,REGRAS_CST!$A$2:$D$200,4,FALSE),"")) | S5: =IF($H5="","",$H5*(1-$U5)) -> 0.009 | T5: =IF($I5="","",$I5*(1-$U5)) -> 0.001 | U5: =IFERROR(INDEX(BASE_CCLASSTRIB!$E:$E, MATCH(TEXT($D5,"000000"), BASE_CCLASSTRIB!$A:$A, 0))/100, 0) -> 0 | V5: =IFERROR(INDEX(BASE_CCLASSTRIB!$F:$F, MATCH(TEXT($D5,"000000"), BASE_CCLASSTRIB!$A:$A, 0))/100, 0) -> 0
E6: =IF(D6="","",LEFT(D6,3)) | F6: =IF(E6="","",IFERROR(VLOOKUP(E6,REGRAS_CST!$A$2:$B$200,2,FALSE),"")) | H6: 0.009 | I6: 0.001 | K6: =IF(E6="","",IFERROR(VLOOKUP(E6,REGRAS_CST!$A$2:$C$200,3,FALSE),"")) | L6: =IF($G6="", "", $G6*(1-$V6)) | M6: =IF(OR($L6="",$S6=""),"",$L6*$S6) | N6: =IF(OR($L6="",$T6=""),"",$L6*$T6) | O6: =IF(D6="","", IF(AND(K6<>"SIM",V6>0),"ERRO: % BC > 0, mas NÃO permitida ❌", IF(AND(K6="SIM",V6=0),"ATENÇÃO: BC permitida, mas % = 0 🔎", "Base de cálculo aplicada corretamente ✅"))) | P6: =IF(D6="","", IF(AND(Q6<>"SIM",U6>0),"ERRO: % alíquota > 0, mas NÃO permitida ❌", IF(AND(Q6="SIM",U6=0),"ATENÇÃO: alíquota permitida, mas % = 0 🔎", "Alíquota aplicada corretamente ✅"))) | Q6: =IF(E6="","",IFERROR(VLOOKUP(E6,REGRAS_CST!$A$2:$D$200,4,FALSE),"")) | S6: =IF($H6="","",$H6*(1-$U6)) -> 0.009 | T6: =IF($I6="","",$I6*(1-$U6)) -> 0.001 | U6: =IFERROR(INDEX(BASE_CCLASSTRIB!$E:$E, MATCH(TEXT($D6,"000000"), BASE_CCLASSTRIB!$A:$A, 0))/100, 0) -> 0 | V6: =IFERROR(INDEX(BASE_CCLASSTRIB!$F:$F, MATCH(TEXT($D6,"000000"), BASE_CCLASSTRIB!$A:$A, 0))/100, 0) -> 0
E7: =IF(D7="","",LEFT(D7,3)) | F7: =IF(E7="","",IFERROR(VLOOKUP(E7,REGRAS_CST!$A$2:$B$200,2,FALSE),"")) | H7: 0.009 | I7: 0.001 | K7: =IF(E7="","",IFERROR(VLOOKUP(E7,REGRAS_CST!$A$2:$C$200,3,FALSE),"")) | L7: =IF($G7="", "", $G7*(1-$V7)) | M7: =IF(OR($L7="",$S7=""),"",$L7*$S7) | N7: =IF(OR($L7="",$T7=""),"",$L7*$T7) | O7: =IF(D7="","", IF(AND(K7<>"SIM",V7>0),"ERRO: % BC > 0, mas NÃO permitida ❌", IF(AND(K7="SIM",V7=0),"ATENÇÃO: BC permitida, mas % = 0 🔎", "Base de cálculo aplicada corretamente ✅"))) | P7: =IF(D7="","", IF(AND(Q7<>"SIM",U7>0),"ERRO: % alíquota > 0, mas NÃO permitida ❌", IF(AND(Q7="SIM",U7=0),"ATENÇÃO: alíquota permitida, mas % = 0 🔎", "Alíquota aplicada corretamente ✅"))) | Q7: =IF(E7="","",IFERROR(VLOOKUP(E7,REGRAS_CST!$A$2:$D$200,4,FALSE),"")) | S7: =IF($H7="","",$H7*(1-$U7)) -> 0.009 | T7: =IF($I7="","",$I7*(1-$U7)) -> 0.001 | U7: =IFERROR(INDEX(BASE_CCLASSTRIB!$E:$E, MATCH(TEXT($D7,"000000"), BASE_CCLASSTRIB!$A:$A, 0))/100, 0) -> 0 | V7: =IFERROR(INDEX(BASE_CCLASSTRIB!$F:$F, MATCH(TEXT($D7,"000000"), BASE_CCLASSTRIB!$A:$A, 0))/100, 0) -> 0
E8: =IF(D8="","",LEFT(D8,3)) | F8: =IF(E8="","",IFERROR(VLOOKUP(E8,REGRAS_CST!$A$2:$B$200,2,FALSE),"")) | H8: 0.009 | I8: 0.001 | K8: =IF(E8="","",IFERROR(VLOOKUP(E8,REGRAS_CST!$A$2:$C$200,3,FALSE),"")) | L8: =IF($G8="", "", $G8*(1-$V8)) | M8: =IF(OR($L8="",$S8=""),"",$L8*$S8) | N8: =IF(OR($L8="",$T8=""),"",$L8*$T8) | O8: =IF(D8="","", IF(AND(K8<>"SIM",V8>0),"ERRO: % BC > 0, mas NÃO permitida ❌", IF(AND(K8="SIM",V8=0),"ATENÇÃO: BC permitida, mas % = 0 🔎", "Base de cálculo aplicada corretamente ✅"))) | P8: =IF(D8="","", IF(AND(Q8<>"SIM",U8>0),"ERRO: % alíquota > 0, mas NÃO permitida ❌", IF(AND(Q8="SIM",U8=0),"ATENÇÃO: alíquota permitida, mas % = 0 🔎", "Alíquota aplicada corretamente ✅"))) | Q8: =IF(E8="","",IFERROR(VLOOKUP(E8,REGRAS_CST!$A$2:$D$200,4,FALSE),"")) | S8: =IF($H8="","",$H8*(1-$U8)) -> 0.009 | T8: =IF($I8="","",$I8*(1-$U8)) -> 0.001 | U8: =IFERROR(INDEX(BASE_CCLASSTRIB!$E:$E, MATCH(TEXT($D8,"000000"), BASE_CCLASSTRIB!$A:$A, 0))/100, 0) -> 0 | V8: =IFERROR(INDEX(BASE_CCLASSTRIB!$F:$F, MATCH(TEXT($D8,"000000"), BASE_CCLASSTRIB!$A:$A, 0))/100, 0) -> 0
E9: =IF(D9="","",LEFT(D9,3)) | F9: =IF(E9="","",IFERROR(VLOOKUP(E9,REGRAS_CST!$A$2:$B$200,2,FALSE),"")) | H9: 0.009 | I9: 0.001 | K9: =IF(E9="","",IFERROR(VLOOKUP(E9,REGRAS_CST!$A$2:$C$200,3,FALSE),"")) | L9: =IF($G9="", "", $G9*(1-$V9)) | M9: =IF(OR($L9="",$S9=""),"",$L9*$S9) | N9: =IF(OR($L9="",$T9=""),"",$L9*$T9) | O9: =IF(D9="","", IF(AND(K9<>"SIM",V9>0),"ERRO: % BC > 0, mas NÃO permitida ❌", IF(AND(K9="SIM",V9=0),"ATENÇÃO: BC permitida, mas % = 0 🔎", "Base de cálculo aplicada corretamente ✅"))) | P9: =IF(D9="","", IF(AND(Q9<>"SIM",U9>0),"ERRO: % alíquota > 0, mas NÃO permitida ❌", IF(AND(Q9="SIM",U9=0),"ATENÇÃO: alíquota permitida, mas % = 0 🔎", "Alíquota aplicada corretamente ✅"))) | Q9: =IF(E9="","",IFERROR(VLOOKUP(E9,REGRAS_CST!$A$2:$D$200,4,FALSE),"")) | S9: =IF($H9="","",$H9*(1-$U9)) -> 0.009 | T9: =IF($I9="","",$I9*(1-$U9)) -> 0.001 | U9: =IFERROR(INDEX(BASE_CCLASSTRIB!$E:$E, MATCH(TEXT($D9,"000000"), BASE_CCLASSTRIB!$A:$A, 0))/100, 0) -> 0 | V9: =IFERROR(INDEX(BASE_CCLASSTRIB!$F:$F, MATCH(TEXT($D9,"000000"), BASE_CCLASSTRIB!$A:$A, 0))/100, 0) -> 0
E10: =IF(D10="","",LEFT(D10,3)) | F10: =IF(E10="","",IFERROR(VLOOKUP(E10,REGRAS_CST!$A$2:$B$200,2,FALSE),"")) | H10: 0.009 | I10: 0.001 | K10: =IF(E10="","",IFERROR(VLOOKUP(E10,REGRAS_CST!$A$2:$C$200,3,FALSE),"")) | L10: =IF($G10="", "", $G10*(1-$V10)) | M10: =IF(OR($L10="",$S10=""),"",$L10*$S10) | N10: =IF(OR($L10="",$T10=""),"",$L10*$T10) | O10: =IF(D10="","", IF(AND(K10<>"SIM",V10>0),"ERRO: % BC > 0, mas NÃO permitida ❌", IF(AND(K10="SIM",V10=0),"ATENÇÃO: BC permitida, mas % = 0 🔎", "Base de cálculo aplicada corretamente ✅"))) | P10: =IF(D10="","", IF(AND(Q10<>"SIM",U10>0),"ERRO: % alíquota > 0, mas NÃO permitida ❌", IF(AND(Q10="SIM",U10=0),"ATENÇÃO: alíquota permitida, mas % = 0 🔎", "Alíquota aplicada corretamente ✅"))) | Q10: =IF(E10="","",IFERROR(VLOOKUP(E10,REGRAS_CST!$A$2:$D$200,4,FALSE),"")) | S10: =IF($H10="","",$H10*(1-$U10)) -> 0.009 | T10: =IF($I10="","",$I10*(1-$U10)) -> 0.001 | U10: =IFERROR(INDEX(BASE_CCLASSTRIB!$E:$E, MATCH(TEXT($D10,"000000"), BASE_CCLASSTRIB!$A:$A, 0))/100, 0) -> 0 | V10: =IFERROR(INDEX(BASE_CCLASSTRIB!$F:$F, MATCH(TEXT($D10,"000000"), BASE_CCLASSTRIB!$A:$A, 0))/100, 0) -> 0
E11: =IF(D11="","",LEFT(D11,3)) | F11: =IF(E11="","",IFERROR(VLOOKUP(E11,REGRAS_CST!$A$2:$B$200,2,FALSE),"")) | H11: 0.009 | I11: 0.001 | K11: =IF(E11="","",IFERROR(VLOOKUP(E11,REGRAS_CST!$A$2:$C$200,3,FALSE),"")) | L11: =IF($G11="", "", $G11*(1-$V11)) | M11: =IF(OR($L11="",$S11=""),"",$L11*$S11) | N11: =IF(OR($L11="",$T11=""),"",$L11*$T11) | O11: =IF(D11="","", IF(AND(K11<>"SIM",V11>0),"ERRO: % BC > 0, mas NÃO permitida ❌", IF(AND(K11="SIM",V11=0),"ATENÇÃO: BC permitida, mas % = 0 🔎", "Base de cálculo aplicada corretamente ✅"))) | P11: =IF(D11="","", IF(AND(Q11<>"SIM",U11>0),"ERRO: % alíquota > 0, mas NÃO permitida ❌", IF(AND(Q11="SIM",U11=0),"ATENÇÃO: alíquota permitida, mas % = 0 🔎", "Alíquota aplicada corretamente ✅"))) | Q11: =IF(E11="","",IFERROR(VLOOKUP(E11,REGRAS_CST!$A$2:$D$200,4,FALSE),"")) | S11: =IF($H11="","",$H11*(1-$U11)) -> 0.009 | T11: =IF($I11="","",$I11*(1-$U11)) -> 0.001 | U11: =IFERROR(INDEX(BASE_CCLASSTRIB!$E:$E, MATCH(TEXT($D11,"000000"), BASE_CCLASSTRIB!$A:$A, 0))/100, 0) -> 0 | V11: =IFERROR(INDEX(BASE_CCLASSTRIB!$F:$F, MATCH(TEXT($D11,"000000"), BASE_CCLASSTRIB!$A:$A, 0))/100, 0) -> 0
E12: =IF(D12="","",LEFT(D12,3)) | F12: =IF(E12="","",IFERROR(VLOOKUP(E12,REGRAS_CST!$A$2:$B$200,2,FALSE),"")) | H12: 0.009 | I12: 0.001 | K12: =IF(E12="","",IFERROR(VLOOKUP(E12,REGRAS_CST!$A$2:$C$200,3,FALSE),"")) | L12: =IF($G12="", "", $G12*(1-$V12)) | M12: =IF(OR($L12="",$S12=""),"",$L12*$S12) | N12: =IF(OR($L12="",$T12=""),"",$L12*$T12) | O12: =IF(D12="","", IF(AND(K12<>"SIM",V12>0),"ERRO: % BC > 0, mas NÃO permitida ❌", IF(AND(K12="SIM",V12=0),"ATENÇÃO: BC permitida, mas % = 0 🔎", "Base de cálculo aplicada corretamente ✅"))) | P12: =IF(D12="","", IF(AND(Q12<>"SIM",U12>0),"ERRO: % alíquota > 0, mas NÃO permitida ❌", IF(AND(Q12="SIM",U12=0),"ATENÇÃO: alíquota permitida, mas % = 0 🔎", "Alíquota aplicada corretamente ✅"))) | Q12: =IF(E12="","",IFERROR(VLOOKUP(E12,REGRAS_CST!$A$2:$D$200,4,FALSE),"")) | S12: =IF($H12="","",$H12*(1-$U12)) -> 0.009 | T12: =IF($I12="","",$I12*(1-$U12)) -> 0.001 | U12: =IFERROR(INDEX(BASE_CCLASSTRIB!$E:$E, MATCH(TEXT($D12,"000000"), BASE_CCLASSTRIB!$A:$A, 0))/100, 0) -> 0 | V12: =IFERROR(INDEX(BASE_CCLASSTRIB!$F:$F, MATCH(TEXT($D12,"000000"), BASE_CCLASSTRIB!$A:$A, 0))/100, 0) -> 0
E13: =IF(D13="","",LEFT(D13,3)) | F13: =IF(E13="","",IFERROR(VLOOKUP(E13,REGRAS_CST!$A$2:$B$200,2,FALSE),"")) | H13: 0.009 | I13: 0.001 | K13: =IF(E13="","",IFERROR(VLOOKUP(E13,REGRAS_CST!$A$2:$C$200,3,FALSE),"")) | L13: =IF($G13="", "", $G13*(1-$V13)) | M13: =IF(OR($L13="",$S13=""),"",$L13*$S13) | N13: =IF(OR($L13="",$T13=""),"",$L13*$T13) | O13: =IF(D13="","", IF(AND(K13<>"SIM",V13>0),"ERRO: % BC > 0, mas NÃO permitida ❌", IF(AND(K13="SIM",V13=0),"ATENÇÃO: BC permitida, mas % = 0 🔎", "Base de cálculo aplicada corretamente ✅"))) | P13: =IF(D13="","", IF(AND(Q13<>"SIM",U13>0),"ERRO: % alíquota > 0, mas NÃO permitida ❌", IF(AND(Q13="SIM",U13=0),"ATENÇÃO: alíquota permitida, mas % = 0 🔎", "Alíquota aplicada corretamente ✅"))) | Q13: =IF(E13="","",IFERROR(VLOOKUP(E13,REGRAS_CST!$A$2:$D$200,4,FALSE),"")) | S13: =IF($H13="","",$H13*(1-$U13)) -> 0.009 | T13: =IF($I13="","",$I13*(1-$U13)) -> 0.001 | U13: =IFERROR(INDEX(BASE_CCLASSTRIB!$E:$E, MATCH(TEXT($D13,"000000"), BASE_CCLASSTRIB!$A:$A, 0))/100, 0) -> 0 | V13: =IFERROR(INDEX(BASE_CCLASSTRIB!$F:$F, MATCH(TEXT($D13,"000000"), BASE_CCLASSTRIB!$A:$A, 0))/100, 0) -> 0
E14: =IF(D14="","",LEFT(D14,3)) | F14: =IF(E14="","",IFERROR(VLOOKUP(E14,REGRAS_CST!$A$2:$B$200,2,FALSE),"")) | H14: 0.009 | I14: 0.001 | K14: =IF(E14="","",IFERROR(VLOOKUP(E14,REGRAS_CST!$A$2:$C$200,3,FALSE),"")) | L14: =IF($G14="", "", $G14*(1-$V14)) | M14: =IF(OR($L14="",$S14=""),"",$L14*$S14) | N14: =IF(OR($L14="",$T14=""),"",$L14*$T14) | O14: =IF(D14="","", IF(AND(K14<>"SIM",V14>0),"ERRO: % BC > 0, mas NÃO permitida ❌", IF(AND(K14="SIM",V14=0),"ATENÇÃO: BC permitida, mas % = 0 🔎", "Base de cálculo aplicada corretamente ✅"))) | P14: =IF(D14="","", IF(AND(Q14<>"SIM",U14>0),"ERRO: % alíquota > 0, mas NÃO permitida ❌", IF(AND(Q14="SIM",U14=0),"ATENÇÃO: alíquota permitida, mas % = 0 🔎", "Alíquota aplicada corretamente ✅"))) | Q14: =IF(E14="","",IFERROR(VLOOKUP(E14,REGRAS_CST!$A$2:$D$200,4,FALSE),"")) | S14: =IF($H14="","",$H14*(1-$U14)) -> 0.009 | T14: =IF($I14="","",$I14*(1-$U14)) -> 0.001 | U14: =IFERROR(INDEX(BASE_CCLASSTRIB!$E:$E, MATCH(TEXT($D14,"000000"), BASE_CCLASSTRIB!$A:$A, 0))/100, 0) -> 0 | V14: =IFERROR(INDEX(BASE_CCLASSTRIB!$F:$F, MATCH(TEXT($D14,"000000"), BASE_CCLASSTRIB!$A:$A, 0))/100, 0) -> 0
... E1737: =IF(D1737="","",LEFT(D1737,3)) | F1737: =IF(E1737="","",IFERROR(VLOOKUP(E1737,REGRAS_CST!$A$2:$B$200,2,FALSE),"")) | H1737: 0.009 | I1737: 0.001 | K1737: =IF(E1737="","",IFERROR(VLOOKUP(E1737,REGRAS_CST!$A$2:$C$200,3,FALSE),"")) | L1737: =IF($G1737="", "", $G1737*(1-$V1737)) | M1737: =IF(OR($L1737="",$S1737=""),"",$L1737*$S1737) | N1737: =IF(OR($L1737="",$T1737=""),"",$L1737*$T1737) | O1737: =IF(D1737="","", IF(AND(K1737<>"SIM",V1737>0),"ERRO: % BC > 0, mas NÃO permitida ❌", IF(AND(K1737="SIM",V1737=0),"ATENÇÃO: BC permitida, mas % = 0 🔎", "Base de cálculo aplicada corretamente ✅"))) | P1737: =IF(D1737="","", IF(AND(Q1737<>"SIM",U1737>0),"ERRO: % alíquota > 0, mas NÃO permitida ❌", IF(AND(Q1737="SIM",U1737=0),"ATENÇÃO: alíquota permitida, mas % = 0 🔎", "Alíquota aplicada corretamente ✅"))) | Q1737: =IF(E1737="","",IFERROR(VLOOKUP(E1737,REGRAS_CST!$A$2:$D$200,4,FALSE),"")) | S1737: =IF($H1737="","",$H1737*(1-$U1737)) -> 0.009 | T1737: =IF($I1737="","",$I1737*(1-$U1737)) -> 0.001 | U1737: =IFERROR(INDEX(BASE_CCLASSTRIB!$E:$E, MATCH(TEXT($D1737,"000000"), BASE_CCLASSTRIB!$A:$A, 0))/100, 0) -> 0 | V1737: =IFERROR(INDEX(BASE_CCLASSTRIB!$F:$F, MATCH(TEXT($D1737,"000000"), BASE_CCLASSTRIB!$A:$A, 0))/100, 0) -> 0

Sheet IMPORT_CCLASSTRIB
A1: =#REF! -> #REF! | B1: =#REF! -> #REF! | C1: =#REF! -> #REF! | D1: =#REF! -> #REF! | E1: =#REF! -> #REF! | F1: =#REF! -> #REF! | G1: =#REF! -> #REF! | H1: =#REF! -> #REF!
A2: =#REF! -> #REF! | B2: =#REF! -> #REF! | C2: =#REF! -> #REF! | D2: =#REF! -> #REF! | E2: =#REF! -> #REF! | F2: =#REF! -> #REF! | G2: =#REF! -> #REF! | H2: =#REF! -> #REF!
A3: =#REF! -> #REF! | B3: =#REF! -> #REF! | C3: =#REF! -> #REF! | D3: =#REF! -> #REF! | E3: =#REF! -> #REF! | F3: =#REF! -> #REF! | G3: =#REF! -> #REF! | H3: =#REF! -> #REF!
A4: =#REF! -> #REF! | B4: =#REF! -> #REF! | C4: =#REF! -> #REF! | D4: =#REF! -> #REF! | E4: =#REF! -> #REF! | F4: =#REF! -> #REF! | G4: =#REF! -> #REF! | H4: =#REF! -> #REF!
A5: =#REF! -> #REF! | B5: =#REF! -> #REF! | C5: =#REF! -> #REF! | D5: =#REF! -> #REF! | E5: =#REF! -> #REF! | F5: =#REF! -> #REF! | G5: =#REF! -> #REF! | H5: =#REF! -> #REF!
A6: =#REF! -> #REF! | B6: =#REF! -> #REF! | C6: =#REF! -> #REF! | D6: =#REF! -> #REF! | E6: =#REF! -> #REF! | F6: =#REF! -> #REF! | G6: =#REF! -> #REF! | H6: =#REF! -> #REF!
A7: =#REF! -> #REF! | B7: =#REF! -> #REF! | C7: =#REF! -> #REF! | D7: =#REF! -> #REF! | E7: =#REF! -> #REF! | F7: =#REF! -> #REF! | G7: =#REF! -> #REF! | H7: =#REF! -> #REF!
A8: =#REF! -> #REF! | B8: =#REF! -> #REF! | C8: =#REF! -> #REF! | D8: =#REF! -> #REF! | E8: =#REF! -> #REF! | F8: =#REF! -> #REF! | G8: =#REF! -> #REF! | H8: =#REF! -> #REF!
A9: =#REF! -> #REF! | B9: =#REF! -> #REF! | C9: =#REF! -> #REF! | D9: =#REF! -> #REF! | E9: =#REF! -> #REF! | F9: =#REF! -> #REF! | G9: =#REF! -> #REF! | H9: =#REF! -> #REF!
A10: =#REF! -> #REF! | B10: =#REF! -> #REF! | C10: =#REF! -> #REF! | D10: =#REF! -> #REF! | E10: =#REF! -> #REF! | F10: =#REF! -> #REF! | G10: =#REF! -> #REF! | H10: =#REF! -> #REF!
A11: =#REF! -> #REF! | B11: =#REF! -> #REF! | C11: =#REF! -> #REF! | D11: =#REF! -> #REF! | E11: =#REF! -> #REF! | F11: =#REF! -> #REF! | G11: =#REF! -> #REF! | H11: =#REF! -> #REF!
A12: =#REF! -> #REF! | B12: =#REF! -> #REF! | C12: =#REF! -> #REF! | D12: =#REF! -> #REF! | E12: =#REF! -> #REF! | F12: =#REF! -> #REF! | G12: =#REF! -> #REF! | H12: =#REF! -> #REF!
... A2000: =#REF! -> #REF! | B2000: =#REF! -> #REF! | C2000: =#REF! -> #REF! | D2000: =#REF! -> #REF! | E2000: =#REF! -> #REF! | F2000: =#REF! -> #REF! | G2000: =#REF! -> #REF! | H2000: =#REF! -> #REF!

Sheet BASE_CCLASSTRIB
A1: cClassTrib | B1: CST | C1: Descrição | D1: Tipo de Alíquota | E1: %Redução Alíquota IBS | F1: %Redução BC IBS | G1: pRedCBS (orig)
A2: 000001 | B2: 000 | C2: Situações tributadas integralmente pelo IBS e CBS. | D2: 2 - Padrão | E2: 0 | F2: 0 | G2: 0
A3: 000002 | B3: 000 | C3: Exploração de via | D3: 2 - Padrão | E3: 0 | F3: 0 | G3: 0
A4: 000003 | B4: 000 | C4: Regime automotivo - projetos incentivados (art. 311) | D4: 2 - Padrão | E4: 0 | F4: 0 | G4: 0
A5: 000004 | B5: 000 | C5: Regime automotivo - projetos incentivados (art. 312) | D5: 2 - Padrão | E5: 0 | F5: 0 | G5: 0
A6: 010001 | B6: 010 | C6: Operações do FGTS não realizadas pela Caixa Econômica Federal | D6: 5 - Uniforme Setorial | E6: 0 | F6: 0 | G6: 0
A7: 010002 | B7: 010 | C7: Operações do serviço financeiro | D7: 5 - Uniforme Setorial | E7: 0 | F7: 0 | G7: 0
A8: 011001 | B8: 011 | C8: Planos de assistência funerária. | D8: 4 - Uniforme Nacional | E8: 60 | F8: 0 | G8: 60
A9: 011002 | B9: 011 | C9: Planos de assistência à saúde | D9: 4 - Uniforme Nacional | E9: 60 | F9: 0 | G9: 60
A10: 011003 | B10: 011 | C10: Intermediação de planos de assistência à saúde | D10: 4 - Uniforme Nacional | E10: 60 | F10: 0 | G10: 60
A11: 011004 | B11: 011 | C11: Concursos e prognósticos | D11: 4 - Uniforme Nacional | E11: 0 | F11: 0 | G11: 0
A12: 011005 | B12: 011 | C12: Planos de assistência à saúde de animais domésticos | D12: 4 - Uniforme Nacional | E12: 30 | F12: 0 | G12: 30
A13: 200001 | B13: 200 | C13: Aquisições realizadas entre empresas autorizadas a operar em zonas de processamento de exportação | D13: 2 - Padrão | E13: 100 | F13: 0 | G13: 100
... A146: 830001 | B146: 830 | C146: Documento com exclusão da BC da CBS e do IBS de energia elétrica fornecida pela distribuidora à UC | D146: 2 - Padrão | E146: 0 | F146: 0 | G146: 0
